test_regress/t/t_fourstate_demo.v
// DESCRIPTION: Verilator: Verilog Test module
//
// This file ONLY is placed under the Creative Commons Public Domain.
// SPDX-FileCopyrightText: 2026 Antmicro
// SPDX-License-Identifier: CC0-1.0

`define STRINGIFY(x) `"x`"

module t;
  bit clk = 1;
  wire x;
  tri y;
  wire t;
  triand u;
  wor z;
  wor z3;
  wor [3:0] z2;
  wire lost;
  wire open = 'z;
  assign x = clk;
  assign z = x;
  assign z = y;
  assign u = z;
  assign u = x;
  assign t = u;
  assign t = x;
  assign t = y;
  wire [128:0] xx;
  logic [128:0] xy;
  logic [128:0] xz;
  bit one = 1;
  always #5 clk <= ~clk;

  always #10 xz = ~xz;
  assign xx = xy;
  assign xx = xz;

  // logic example;
  task writeFourState(logic a);
    if (a === 1'b1) $write("1");
    else if (a === 1'b0) $write("0");
    else if (a === 1'bx) $write("x");
    else if (a === 1'bz) $write("z");
    else $stop;
  endtask
  task print(logic a, logic b);
    // $write(" %1d & %1d == %1d |", a, b, a & b);
    $write(" ");
    writeFourState(a);
    $write(" ^ ");
    writeFourState(b);
    $write(" == ");
    writeFourState(a ^ b);
    $write(" |");
  endtask
  initial begin
    static int n = 12;
    static integer res = 'b01xz | n;
    if ((int'('b01xz | n)) === n);
    else $stop;
    #1;
    xy = 442093479423423857275364882039482723489;
    xz = 442093479423423857275364882039482723489;
    $dumpfile(`STRINGIFY(`TEST_DUMPFILE));
    $dumpvars();
    // $write("HERE: %d\n", res[0]);
    // $write("HERE1: %d\n", res[1]);
    // $write("HERE2: %d\n", res[2]);
    // $write("HERE3: %d\n", res[3]);
    // $write("HERE4: %d\n", res[31]);
    $write("      ZERO       | ONE        | X          | Z      \n");
    $write("ZERO ");
    print(0, 0);
    print(0, 1);
    print(0, 'x);
    print(0, 'z);
    $write("\nONE  ");
    print(1, 0);
    print(1, 1);
    print(1, 'x);
    print(1, 'z);
    $write("\nX    ");
    print('x, 0);
    print('x, 1);
    print('x, 'x);
    print('x, 'z);
    $write("\nZ    ");
    print('z, 0);
    print('z, 1);
    print('z, 'x);
    print('z, 'z);
    $write("\n");
    $write("x wire: ");
    writeFourState(x);
    $write("\n");
    $write("z wor: ");
    writeFourState(z);
    $write("\n");
    $write("u triand: ");
    writeFourState(u);
    $write("\n");
    $write("t wire: ");
    writeFourState(t);
    $write("\n");
    #1;
    $write("x wire: ");
    writeFourState(x);
    $write("\n");
    $write("z wor: ");
    writeFourState(z);
    $write("\n");
    $write("u triand: ");
    writeFourState(u);
    $write("\n");
    $write("t wire: ");
    writeFourState(t);
    $write("\n");
    if ('x & (t !== 0)) $stop;
    else if (t != 0) $stop;
    else if (~(t & one | t)) $stop;
    else if (t | one) $write("Bye\n");
    else $stop;
    #100;
    $finish;
  end
endmodule

test_regress/t/t_fourstate_demo.out.vcd
$version Generated by VerilatedVcd $end
$timescale 1ps $end
 $scope module t $end
  $var wire 1 C clk $end
  $var wire 1 D x $end
  $var wire 1 L y $end
  $var wire 1 F t $end
  $var wire 1 H u $end
  $var wire 1 J z $end
  $var wire 1 N z3 $end
  $var wire 4 P z2 [3:0] $end
  $var wire 1 R lost $end
  $var wire 1 T open $end
  $var wire 129 / xx [128:0] $end
  $var wire 129 % xy [128:0] $end
  $var wire 129 9 xz [128:0] $end
  $var wire 1 V one $end
  $scope module unnamedblk1 $end
   $var wire 32 " n [31:0] $end
   $var wire 32 # res [31:0] $end
  $upscope $end
 $upscope $end
$enddefinitions $end


#1
b00000000000000000000000000001100 "
b000000000000000000000000000011xx #
b101001100100110000001101101100101111011001001111100010101000110000000010101101011101011111000001101010001010101011010110010100001 %
b101001100100110000001101101100101111011001001111100010101000110000000010101101011101011111000001101010001010101011010110010100001 /
b101001100100110000001101101100101111011001001111100010101000110000000010101101011101011111000001101010001010101011010110010100001 9
1C
1D
xF
1H
1J
xL
xN
bxxxx P
xR
zT
1V
#5
0C
0D
0H
xJ
#10
bxxxxxxxxxxxxxxxxxxxxxxxxxxxxxxxxxxxxxxxxxxxxxxxxxxxxxxxxxxxxxxxxxxxxxxxxxxxxxxxxxxxxxxxxxxxxxxxxxxxxxxxxxxxxxxxxxxxxxxxxxxxxxxxxx /
b010110011011001111110010010011010000100110110000011101010111001111111101010010100010100000111110010101110101010100101001101011110 9
1C
1D
1H
1J
#15
0C
0D
0H
xJ
#20
b101001100100110000001101101100101111011001001111100010101000110000000010101101011101011111000001101010001010101011010110010100001 /
b101001100100110000001101101100101111011001001111100010101000110000000010101101011101011111000001101010001010101011010110010100001 9
1C
1D
1H
1J
#25
0C
0D
0H
xJ
#30
bxxxxxxxxxxxxxxxxxxxxxxxxxxxxxxxxxxxxxxxxxxxxxxxxxxxxxxxxxxxxxxxxxxxxxxxxxxxxxxxxxxxxxxxxxxxxxxxxxxxxxxxxxxxxxxxxxxxxxxxxxxxxxxxxx /
b010110011011001111110010010011010000100110110000011101010111001111111101010010100010100000111110010101110101010100101001101011110 9
1C
1D
1H
1J
#35
0C
0D
0H
xJ
#40
b101001100100110000001101101100101111011001001111100010101000110000000010101101011101011111000001101010001010101011010110010100001 /
b101001100100110000001101101100101111011001001111100010101000110000000010101101011101011111000001101010001010101011010110010100001 9
1C
1D
1H
1J
#45
0C
0D
0H
xJ
#50
bxxxxxxxxxxxxxxxxxxxxxxxxxxxxxxxxxxxxxxxxxxxxxxxxxxxxxxxxxxxxxxxxxxxxxxxxxxxxxxxxxxxxxxxxxxxxxxxxxxxxxxxxxxxxxxxxxxxxxxxxxxxxxxxxx /
b010110011011001111110010010011010000100110110000011101010111001111111101010010100010100000111110010101110101010100101001101011110 9
1C
1D
1H
1J
#55
0C
0D
0H
xJ
#60
b101001100100110000001101101100101111011001001111100010101000110000000010101101011101011111000001101010001010101011010110010100001 /
b101001100100110000001101101100101111011001001111100010101000110000000010101101011101011111000001101010001010101011010110010100001 9
1C
1D
1H
1J
#65
0C
0D
0H
xJ
#70
bxxxxxxxxxxxxxxxxxxxxxxxxxxxxxxxxxxxxxxxxxxxxxxxxxxxxxxxxxxxxxxxxxxxxxxxxxxxxxxxxxxxxxxxxxxxxxxxxxxxxxxxxxxxxxxxxxxxxxxxxxxxxxxxxx /
b010110011011001111110010010011010000100110110000011101010111001111111101010010100010100000111110010101110101010100101001101011110 9
1C
1D
1H
1J
#75
0C
0D
0H
xJ
#80
b101001100100110000001101101100101111011001001111100010101000110000000010101101011101011111000001101010001010101011010110010100001 /
b101001100100110000001101101100101111011001001111100010101000110000000010101101011101011111000001101010001010101011010110010100001 9
1C
1D
1H
1J
#85
0C
0D
0H
xJ
#90
bxxxxxxxxxxxxxxxxxxxxxxxxxxxxxxxxxxxxxxxxxxxxxxxxxxxxxxxxxxxxxxxxxxxxxxxxxxxxxxxxxxxxxxxxxxxxxxxxxxxxxxxxxxxxxxxxxxxxxxxxxxxxxxxxx /
b010110011011001111110010010011010000100110110000011101010111001111111101010010100010100000111110010101110101010100101001101011110 9
1C
1D
1H
1J
#95
0C
0D
0H
xJ
#100
b101001100100110000001101101100101111011001001111100010101000110000000010101101011101011111000001101010001010101011010110010100001 /
b101001100100110000001101101100101111011001001111100010101000110000000010101101011101011111000001101010001010101011010110010100001 9
1C
1D
1H
1J
