test_regress/t/t_x_sim_demo.v
// DESCRIPTION: Verilator: Verilog Test module
//
// This file ONLY is placed under the Creative Commons Public Domain.
// SPDX-FileCopyrightText: 2026 Antmicro
// SPDX-License-Identifier: CC0-1.0

`define STRINGIFY(x) `"x`"

module t;
  bit clk = 1;
  wire x = 1;
  tri y = 0;
  wire t = 'z;
  triand u;
  wor z;
  wor z3;
  wor [3:0] z2;
  wire lost;
  wire open = 'z;
  time time_test = 7;
  assign x = clk;
  assign z = x;
  assign z = y;
  assign u = z;
  assign u = x;
  assign t = u;
  assign t = x;
  assign t = y;
  bit one = 1;
  always #5 clk <= ~clk;
  // logic example;
  task print(logic a, logic b);
    $write(" %1d & %1d == %1d |", a, b, a & b);
  endtask
  initial begin
    static int n = 8;
    static integer res = 'b01xz | n;
    $dumpfile(`STRINGIFY(`TEST_DUMPFILE));
    $dumpvars();
    $write("HERE: %d\n", res[0]);
    $write("HERE1: %d\n", res[1]);
    $write("HERE2: %d\n", res[2]);
    $write("HERE3: %d\n", res[3]);
    $write("HERE4: %d\n", res[31]);
    $write("      ZERO       | ONE        | X          | Z      \n");
    $write("ZERO ");
    print(0, 0);
    print(0, 1);
    print(0, 'x);
    print(0, 'z);
    $write("\nONE  ");
    print(1, 0);
    print(1, 1);
    print(1, 'x);
    print(1, 'z);
    $write("\nX    ");
    print('x, 0);
    print('x, 1);
    print('x, 'x);
    print('x, 'z);
    $write("\nZ    ");
    print('z, 0);
    print('z, 1);
    print('z, 'x);
    print('z, 'z);
    $write("\n");
    $write("x wire: %d\n", x);
    $write("z wor: %d\n", z);
    $write("u triand: %d\n", u);
    $write("t wire: %d\n", t);
    #1;
    $write("x wire: %d\n", x);
    $write("z wor: %d\n", z);
    $write("u triand: %d\n", u);
    $write("t wire: %d\n", t);
    if (~(t & one | t)) $stop;
    else if (t | one) $write("Bye\n");
    else $stop;
    #100;
    $finish;
  end
endmodule

test_regress/t/t_x_sim_demo.out.vcd
$version Generated by VerilatedVcd $end
$timescale 1ps $end
 $scope module t $end
  $var wire 1 ' clk $end
  $var wire 1 , x $end
  $var wire 1 . y $end
  $var wire 1 0 t $end
  $var wire 1 ( u $end
  $var wire 1 * z $end
  $var wire 1 7 z3 $end
  $var wire 4 9 z2 [3:0] $end
  $var wire 1 ; lost $end
  $var wire 1 2 open $end
  $var wire 64 " time_test [63:0] $end
  $var wire 1 & one $end
  $scope module unnamedblk1 $end
   $var wire 32 4 n [31:0] $end
   $var wire 32 5 res [31:0] $end
  $upscope $end
 $upscope $end
$enddefinitions $end


#0
b0000000000000000000000000000000000000000000000000000000000000111 "
1&
1'
1(
1*
1,
0.
x0
z2
b00000000000000000000000000001000 4
b000000000000000000000000000011xx 5
x7
bxxxx 9
x;
#5
0'
0(
0*
0,
00
#10
1'
1(
1*
1,
x0
#15
0'
0(
0*
0,
00
#20
1'
1(
1*
1,
x0
#25
0'
0(
0*
0,
00
#30
1'
1(
1*
1,
x0
#35
0'
0(
0*
0,
00
#40
1'
1(
1*
1,
x0
#45
0'
0(
0*
0,
00
#50
1'
1(
1*
1,
x0
#55
0'
0(
0*
0,
00
#60
1'
1(
1*
1,
x0
#65
0'
0(
0*
0,
00
#70
1'
1(
1*
1,
x0
#75
0'
0(
0*
0,
00
#80
1'
1(
1*
1,
x0
#85
0'
0(
0*
0,
00
#90
1'
1(
1*
1,
x0
#95
0'
0(
0*
0,
00
#100
1'
1(
1*
1,
x0
