test_regress/t/t_x_sim_demo2.v
// DESCRIPTION: Verilator: Verilog Test module
//
// This file ONLY is placed under the Creative Commons Public Domain.
// SPDX-FileCopyrightText: 2026 Antmicro
// SPDX-License-Identifier: CC0-1.0

`define STRINGIFY(x) `"x`"

module counter(input clk, input rstn, output reg[3:0] out);
  always @(posedge clk) begin
    if (!rstn) out <= 0;
    else out <= out + 1;
  end
endmodule

module tb_counter;
  reg clk;
  reg rstn;
  wire [3:0] out;

  counter c(.clk (clk),
            .rstn (rstn),
            .out (out));

  always #5 begin
    if (clk) $write("[out] %d\n", out);
    clk = ~clk;
  end

  initial begin
    $dumpfile(`STRINGIFY(`TEST_DUMPFILE));
    $dumpvars();
    #20 rstn <= 1;
    #20 clk <= 0;

    #25 rstn <= 1;
    #20 rstn <= 0;
    #10 rstn <= 1;

    #100 $finish;
  end
endmodule

test_regress/t/t_x_sim_demo2.out.vcd
$version Generated by VerilatedVcd $end
$timescale 1ps $end
 $scope module tb_counter $end
  $var wire 1 " clk $end
  $var wire 1 $ rstn $end
  $var wire 4 & out [3:0] $end
  $scope module c $end
   $var wire 1 ( clk $end
   $var wire 1 * rstn $end
   $var wire 4 , out [3:0] $end
  $upscope $end
 $upscope $end
$enddefinitions $end


#0
x"
x$
bxxxx &
x(
x*
bxxxx ,
#20
1$
1*
#40
1"
1(
#45
0"
0(
#50
1"
1(
#55
0"
0(
#60
1"
1(
#65
0"
0(
#70
1"
1(
#75
0"
0(
#80
1"
1(
#85
0"
0$
0(
0*
#90
1"
b0000 &
1(
b0000 ,
#95
0"
1$
0(
1*
#100
1"
b0001 &
1(
b0001 ,
#105
0"
0(
#110
1"
b0010 &
1(
b0010 ,
#115
0"
0(
#120
1"
b0011 &
1(
b0011 ,
#125
0"
0(
#130
1"
b0100 &
1(
b0100 ,
#135
0"
0(
#140
1"
b0101 &
1(
b0101 ,
#145
0"
0(
#150
1"
b0110 &
1(
b0110 ,
#155
0"
0(
#160
1"
b0111 &
1(
b0111 ,
#165
0"
0(
#170
1"
b1000 &
1(
b1000 ,
#175
0"
0(
#180
1"
b1001 &
1(
b1001 ,
#185
0"
0(
#190
1"
b1010 &
1(
b1010 ,
