4-state-demo/d2.sv
module tb_counter;
  reg clk;
  reg rstn;
  reg [3:0] out;

  always @(posedge clk) begin
    if (!rstn) out <= 0;
    else out <= out + 1;
  end

  always #5 begin
    if (clk) $write("[out] %d\n", out);
    clk = ~clk;
  end

  initial begin
    $dumpfile("file2.vcd");
    $dumpvars();
    clk <= 0;

    #20 rstn <= 1;
    #20 rstn <= 0;
    #10 rstn <= 1;
    #80 out <= 'x;

    #20 $finish;
  end
endmodule

4-state-demo/file2.vcd
$version Generated by VerilatedVcd $end
$timescale 1ps $end
 $scope module tb_counter $end
  $var wire 1 " clk $end
  $var wire 1 $ rstn $end
  $var wire 4 & out [3:0] $end
 $upscope $end
$enddefinitions $end


#0
0"
x$
bxxxx &
#5
1"
#10
0"
#15
1"
#20
0"
1$
#25
1"
#30
0"
#35
1"
#40
0"
0$
#45
1"
b0000 &
#50
0"
1$
#55
1"
b0001 &
#60
0"
#65
1"
b0010 &
#70
0"
#75
1"
b0011 &
#80
0"
#85
1"
b0100 &
#90
0"
#95
1"
b0101 &
#100
0"
#105
1"
b0110 &
#110
0"
#115
1"
b0111 &
#120
0"
#125
1"
b1000 &
#130
0"
bxxxx &
